{"email":"mihael@xakep.ru","name":"Misha","text":"Hello World","date":"01.27.2016"}
{"email":"mihael@xakep.ru","name":"Misha","text":"Hello World","date":"01.27.2016"}
{"email":"mihael@xakep.ru","name":"Misha","text":"Hello World","date":"01.27.2016"}
{"email":"mihael@xakep.ru","name":"Misha","text":"Hello World!!!","date":"01.27.2016"}
{"email":"m@m.m","name":"dsg","text":"dfgd","date":"04.03.2016"}
{"email":"dsg","name":"dgd","text":"gdfsg","date":"04.03.2016"}
{"email":"sfsdf","name":"sdfdsf","text":"fsdf","date":"04.03.2016"}
{"email":"fsdf","name":"dfsdf","text":"fdsfs","date":"04.03.2016"}
{"email":"sdds","name":"sdfsad","text":"fsadfsdf","date":"04.03.2016"}
{"email":"sadf","name":"sdfasd","text":"fsfasdf","date":"04.03.2016"}
